itacart/__init__.py
itacart-0.1.0a3.dist-info/licenses/LICENSE
itacart-0.1.0a3.dist-info/METADATA
itacart-0.1.0a3.dist-info/WHEEL
itacart-0.1.0a3.dist-info/top_level.txt
itacart-0.1.0a3.dist-info/RECORD
